Metadata-Version: 2.1
Name: pygalmesh
Version: 0.10.7
Summary: Python frontend to CGAL's mesh generation capabilities
Home-page: https://github.com/nschloe/pygalmesh
Author: Nico Schlömer
Author-email: nico.schloemer@gmail.com
License: GPL-3.0-or-later
Project-URL: Code, https://github.com/nschloe/pygalmesh
Project-URL: Issues, https://github.com/nschloe/pygalmesh/issues
Project-URL: Funding, https://github.com/sponsors/nschloe
Keywords: mathematics,physics,engineering,cgal,mesh,mesh generation
Classifier: Development Status :: 4 - Beta
Classifier: License :: OSI Approved :: GNU General Public License v3 or later (GPLv3+)
Classifier: Operating System :: OS Independent
Classifier: Programming Language :: Python :: 3
Classifier: Programming Language :: Python :: 3.7
Classifier: Programming Language :: Python :: 3.8
Classifier: Programming Language :: Python :: 3.9
Classifier: Programming Language :: Python :: 3.10
Classifier: Topic :: Scientific/Engineering
Classifier: Topic :: Scientific/Engineering :: Mathematics
Classifier: Topic :: Scientific/Engineering :: Physics
Classifier: Topic :: Scientific/Engineering :: Visualization
Requires-Python: >=3.7
License-File: LICENSE
